{"version":1,"resource":"vscode-remote://970-cs-4c43380d-fe76-4983-b149-611a7ef95c9f.cs-asia-southeast1-ajrg.cloudshell.dev/home/dhruv_patil284/file-metadata-pipeline/watch_folder.py","entries":[{"id":"QITW.py","timestamp":1751014270532},{"id":"kQ6D.py","timestamp":1751014516584},{"id":"qwhv.py","timestamp":1751014533252},{"id":"xSxK.py","timestamp":1751014550746},{"id":"68xc.py","timestamp":1751014583686},{"id":"bv6n.py","timestamp":1751014614644},{"id":"w0UE.py","timestamp":1751014660960},{"id":"2zNA.py","timestamp":1751032434818},{"id":"sjJp.py","timestamp":1751032523227}]}